odoo/addons/sales_team_security_sale/README.rst
odoo/addons/sales_team_security_sale/__init__.py
odoo/addons/sales_team_security_sale/__manifest__.py
odoo/addons/sales_team_security_sale/i18n/sales_team_security_sale.pot
odoo/addons/sales_team_security_sale/migrations/14.0.2.0.0/pre-migration.py
odoo/addons/sales_team_security_sale/readme/CONTRIBUTORS.rst
odoo/addons/sales_team_security_sale/readme/DESCRIPTION.rst
odoo/addons/sales_team_security_sale/security/security.xml
odoo/addons/sales_team_security_sale/static/description/icon.png
odoo/addons/sales_team_security_sale/static/description/index.html
odoo/addons/sales_team_security_sale/tests/__init__.py
odoo/addons/sales_team_security_sale/tests/test_sales_team_security_sale.py
odoo14_addon_sales_team_security_sale-14.0.3.0.1.dist-info/METADATA
odoo14_addon_sales_team_security_sale-14.0.3.0.1.dist-info/WHEEL
odoo14_addon_sales_team_security_sale-14.0.3.0.1.dist-info/top_level.txt
odoo14_addon_sales_team_security_sale-14.0.3.0.1.dist-info/RECORD
